<?xml version="1.0"?>
<openerp>
    <data>

     <!--  Exporter Statements Form View -->
     <record model="ir.ui.view" id="view_account_exporter_statements_form">
            <field name="name">account.exporter.statements.form</field>
            <field name="model">account.exporter.statements</field>
            <field name="arch" type="xml">
                <form string="Exporter Statements">
                    <group>       
                        <group>      
                            <field name="partner_id" required="1"/>     
                            <field name="letter_date" required="1"/> 
                            <field name="letter_type" required="1"/>        
                            <field name="vat_code_id"
                                   required="1" />
                            <field name="max_amount" required="1"/>    
                            <field name="period_start" required="1"/> 
                            <field name="period_end" required="1"/>        
                            <field name="letter_status" required="1"/>
                         </group>
                         <group> 
                             <field name="letter_number" required="1"/>
                            <field name="name" />
                        </group>
                    </group>
                </form>
            </field>
     </record>

    <!--  Exporter Statements Tree View -->
    <record model="ir.ui.view" id="view_account_exporter_statements_tree">
            <field name="name">account.exporter.statements.tree</field>
            <field name="model">account.exporter.statements</field>
            <field name="arch" type="xml">
                <tree string="Exporter Statements">
                    <field name="partner_id" />        
                    <field name="letter_number" />
                    <field name="letter_date" /> 
                    <field name="letter_type" />        
                    <field name="vat_code_id" />
                    <field name="max_amount" /> 
                    <field name="period_start" /> 
                    <field name="period_end" />        
                    <field name="letter_status"/>                 
                </tree>
            </field>
    </record>

    <!--  Exporter Statements Search View-->
    <record model="ir.ui.view" id="view_account_exporter_statements_search">
        <field name="name">account.exporter.statements.search</field>
        <field name="model">account.exporter.statements</field>
        <field name="arch" type="xml">
            <search string="Exporter Statements Search">     
                <field name="partner_id" />        
                <field name="letter_number" />
            </search>
        </field>
    </record>

    <!--  Exporter Statements Action -->
    <record model="ir.actions.act_window" id="action_account_exporter_statements">
        <field name="name">Exporter Statements</field>
        <field name="res_model">account.exporter.statements</field>
        <field name="view_type">form</field>
        <field name="view_mode">tree,form</field>
        <field name="search_view_id" ref="view_account_exporter_statements_search"/>
    </record>
    
    <!-- Menu item -->
    <menuitem name="Exporter Statements" parent="account.menu_finance"
         id="account_exporter_statements" sequence="11" />

    <menuitem name="Exporter Statements" parent="account_exporter_statements" id="account_exporter_statements2" action="action_account_exporter_statements" sequence="22"/> 

    </data>
</openerp>
