<?xml version="1.0"?>
<openerp>
    <data>

        <record id="view_invoice_tree_omniapart" model="ir.ui.view">
            <field name="name">view.invoice.tree.omniapart</field>
            <field name="model">account.invoice</field>
            <field name="inherit_id" ref="account.invoice_tree"/>
            <field name="arch" type="xml">
                <xpath expr="//field[@name='amount_untaxed']" position="attributes">
					<attribute name="string">Imponibile</attribute>
                </xpath>
				<xpath expr="//field[@name='registration_date']" position="after"> 
				    <field name="f_protocol_number"/>
				    <field name="supplier_invoice_number" invisible="context.get('type',False) in ['out_invoice','out_refund']"/> 
			    </xpath>                 
            </field>
        </record>       

        <record id="view_invoice_form_omniapart" model="ir.ui.view">
            <field name="name">view.invoice.form.omniapart</field>
            <field name="model">account.invoice</field>
            <field name="inherit_id" ref="account.invoice_form"/>
            <field name="arch" type="xml">
				<xpath expr="//field[@name='registration_date']" position="attributes"> 
				    <attribute name="on_change">onchange_registration_date_customer(date_invoice, registration_date)</attribute> 
			    </xpath>                 
            </field>
        </record>              
        
    </data>
</openerp>
